series_forcastability/__init__.py
series_forcastability/main.py
series_forcastability-0.0.2.dist-info/LICENSE
series_forcastability-0.0.2.dist-info/METADATA
series_forcastability-0.0.2.dist-info/WHEEL
series_forcastability-0.0.2.dist-info/top_level.txt
series_forcastability-0.0.2.dist-info/RECORD
